django_spring/__init__.py
django_spring/app_server.py
django_spring/app_setup.py
django_spring/client.py
django_spring/config.py
django_spring/manager.py
django_spring/utils/__init__.py
django_spring/utils/autoreload.py
django_spring/utils/logger.py
django_spring/utils/preload.py
django_spring/utils/processes.py
django_spring/utils/socket_data.py
django_spring/utils/tty.py
django_spring-0.3.0.data/scripts/spring
django_spring-0.3.0.dist-info/LICENSE
django_spring-0.3.0.dist-info/METADATA
django_spring-0.3.0.dist-info/WHEEL
django_spring-0.3.0.dist-info/top_level.txt
django_spring-0.3.0.dist-info/RECORD
